mdyx/__init__.py
mdyx-0.1.0.dist-info/METADATA
mdyx-0.1.0.dist-info/WHEEL
mdyx-0.1.0.dist-info/RECORD
